lsp_types/__init__.py
lsp_types/methods.py
lsp_types/pool.py
lsp_types/process.py
lsp_types/requests.py
lsp_types/semantic_tokens.py
lsp_types/session.py
lsp_types/types.py
lsp_types/pyrefly/KNOWN_LIMITATIONS.md
lsp_types/pyrefly/__init__.py
lsp_types/pyrefly/backend.py
lsp_types/pyrefly/config_schema.py
lsp_types/pyright/__init__.py
lsp_types/pyright/backend.py
lsp_types/pyright/config_schema.py
lsp_types/ty/KNOWN_LIMITATIONS.md
lsp_types/ty/__init__.py
lsp_types/ty/backend.py
lsp_types/ty/config_schema.py
lsp_types-0.16.0.dist-info/METADATA
lsp_types-0.16.0.dist-info/WHEEL
lsp_types-0.16.0.dist-info/licenses/LICENSE
lsp_types-0.16.0.dist-info/RECORD
