Metadata-Version: 2.4
Name: lsp-types
Version: 0.16.0
Summary: Zero-dependency Python library for Language Server Protocol types
Project-URL: Homepage, https://github.com/mazyod/lsp-python-types
Project-URL: Repository, https://github.com/mazyod/lsp-python-types
Project-URL: Documentation, https://github.com/mazyod/lsp-python-types#readme
Author-email: Mazyad Alabduljaleel <mazjaleel@gmail.com>
License-Expression: MIT
License-File: LICENSE
Keywords: development-tools,editor-tools,ide,language-server-protocol,lsp
Classifier: Development Status :: 4 - Beta
Classifier: Intended Audience :: Developers
Classifier: License :: OSI Approved :: MIT License
Classifier: Programming Language :: Python :: 3
Classifier: Programming Language :: Python :: 3.12
Classifier: Programming Language :: Python :: 3.13
Classifier: Programming Language :: Python :: 3.14
Classifier: Topic :: Software Development :: Libraries :: Python Modules
Classifier: Topic :: Text Editors :: Integrated Development Environments (IDE)
Classifier: Typing :: Typed
Requires-Python: >=3.12
Requires-Dist: tomli-w>=1.0.0
Provides-Extra: pyrefly
Requires-Dist: pyrefly>=0.32.0; extra == 'pyrefly'
